[
    {
        "id": "e8354e20-ac84-42a4-9a86-6eb3782fcb12",
        "owner_id": "f21f2950-7d7d-45cd-93f2-edbb6165e6cd",
        "parent_id": null,
        "slug": "governos-do-mundo-todo-decidem-suspender-pratica-de-adicionar-segundos-bissextos-para-manter-relogios-oficiais-sincronizados-com-a-rotacao-da-terra",
        "title": "Governos do mundo todo decidem suspender pr\u00e1tica de adicionar \u201csegundos bissextos\u201d para manter rel\u00f3gios oficiais sincronizados com a rota\u00e7\u00e3o da Terra",
        "status": "published",
        "type": "content",
        "source_url": "https://www.nature.com/articles/d41586-022-03783-5",
        "created_at": "2022-11-18T20:09:43.439Z",
        "updated_at": "2022-11-18T20:09:43.439Z",
        "published_at": "2022-11-18T20:09:43.472Z",
        "deleted_at": null,
        "owner_username": "FlaviaCarvalho",
        "tabcoins": 3,
        "tabcoins_credit": 2,
        "tabcoins_debit": 0,
        "children_deep_count": 0
    },
    {
        "id": "bc8b3aca-7bae-411b-861b-42c08144d449",
        "owner_id": "f21f2950-7d7d-45cd-93f2-edbb6165e6cd",
        "parent_id": null,
        "slug": "relatorio-anual-da-mozilla-revela-que-seus-esforcos-para-ir-alem-do-navegador-firefox-estao-comecando-a-dar-frutos",
        "title": "Relat\u00f3rio anual da Mozilla revela que seus esfor\u00e7os para ir al\u00e9m do navegador Firefox est\u00e3o come\u00e7ando a dar frutos",
        "status": "published",
        "type": "content",
        "source_url": "https://techcrunch.com/2022/11/17/mozilla-looks-to-its-next-chapter/",
        "created_at": "2022-11-18T18:45:54.625Z",
        "updated_at": "2022-11-18T18:45:54.625Z",
        "published_at": "2022-11-18T18:45:54.643Z",
        "deleted_at": null,
        "owner_username": "FlaviaCarvalho",
        "tabcoins": 3,
        "tabcoins_credit": 2,
        "tabcoins_debit": 0,
        "children_deep_count": 1
    },
    {
        "id": "bff0e9b6-450f-485e-8afd-3373b04c1143",
        "owner_id": "f21f2950-7d7d-45cd-93f2-edbb6165e6cd",
        "parent_id": null,
        "slug": "intel-desenvolve-primeiro-detector-de-deepfake-em-tempo-real-e-com-taxa-de-precisao-de-96-por-cento",
        "title": "Intel desenvolve primeiro detector de deepfake em tempo real e com taxa de precis\u00e3o de 96%",
        "status": "published",
        "type": "content",
        "source_url": "https://venturebeat.com/ai/intel-unveils-real-time-deepfake-detector-claims-96-accuracy-rate/",
        "created_at": "2022-11-18T18:41:47.863Z",
        "updated_at": "2022-11-18T18:41:47.863Z",
        "published_at": "2022-11-18T18:41:47.896Z",
        "deleted_at": null,
        "owner_username": "FlaviaCarvalho",
        "tabcoins": 3,
        "tabcoins_credit": 2,
        "tabcoins_debit": 0,
        "children_deep_count": 0
    },
    {
        "id": "ae4ddc3c-a091-4586-8d3c-dd6afd2a5207",
        "owner_id": "f21f2950-7d7d-45cd-93f2-edbb6165e6cd",
        "parent_id": null,
        "slug": "nsa-agencia-de-seguranca-nacional-dos-eua-quer-colaborar-com-pesquisadores-externos-em-um-novo-escritorio-de-facil-acesso-sem-armas-guardas-ou-portoes",
        "title": "NSA, Ag\u00eancia de Seguran\u00e7a Nacional dos EUA, quer colaborar com pesquisadores externos em um novo escrit\u00f3rio de f\u00e1cil acesso, sem armas, guardas ou port\u00f5es",
        "status": "published",
        "type": "content",
        "source_url": "https://www.cyberscoop.com/nsa-threat-sharing-unclassified-ccc/",
        "created_at": "2022-11-18T18:37:22.731Z",
        "updated_at": "2022-11-18T18:37:22.731Z",
        "published_at": "2022-11-18T18:37:22.751Z",
        "deleted_at": null,
        "owner_username": "FlaviaCarvalho",
        "tabcoins": 1,
        "tabcoins_credit": 0,
        "tabcoins_debit": 0,
        "children_deep_count": 0
    },
    {
        "id": "63753424-68fd-4d9a-8bf0-fe07710e347a",
        "owner_id": "f21f2950-7d7d-45cd-93f2-edbb6165e6cd",
        "parent_id": null,
        "slug": "veiculos-eletricos-sao-mais-simples-de-produzir-e-requerem-cerca-de-40-por-cento-menos-mao-de-obra-diz-ceo-da-ford",
        "title": "Ve\u00edculos el\u00e9tricos s\u00e3o mais simples de produzir e requerem cerca de 40% menos m\u00e3o de obra, diz CEO da Ford",
        "status": "published",
        "type": "content",
        "source_url": "https://cleantechnica.com/2022/11/16/ford-ceo-40-less-labor-to-build-electric-vehicles/",
        "created_at": "2022-11-18T18:31:50.281Z",
        "updated_at": "2022-11-18T18:31:50.281Z",
        "published_at": "2022-11-18T18:31:50.306Z",
        "deleted_at": null,
        "owner_username": "FlaviaCarvalho",
        "tabcoins": 1,
        "tabcoins_credit": 0,
        "tabcoins_debit": 0,
        "children_deep_count": 0
    },
    {
        "id": "04ce7c3a-c63c-4c81-af68-d18b4abef61b",
        "owner_id": "f21f2950-7d7d-45cd-93f2-edbb6165e6cd",
        "parent_id": null,
        "slug": "brasil-e-o-segundo-pais-do-mundo-em-maturidade-de-governo-digital-mostra-indice-do-banco-mundial",
        "title": "Brasil \u00e9 o segundo pa\u00eds do mundo em maturidade de governo digital, mostra \u00edndice do Banco Mundial",
        "status": "published",
        "type": "content",
        "source_url": "https://agenciabrasil.ebc.com.br/geral/noticia/2022-11/brasil-se-torna-segundo-pais-em-maturidade-de-governo-digital",
        "created_at": "2022-11-18T18:31:11.100Z",
        "updated_at": "2022-11-18T18:31:11.100Z",
        "published_at": "2022-11-18T18:31:11.125Z",
        "deleted_at": null,
        "owner_username": "FlaviaCarvalho",
        "tabcoins": 1,
        "tabcoins_credit": 0,
        "tabcoins_debit": 0,
        "children_deep_count": 0
    },
    {
        "id": "32851db1-62cd-4ab5-a0ed-e79780413a0b",
        "owner_id": "88480bef-5da9-4290-ad70-f607c12c93c2",
        "parent_id": null,
        "slug": "regras-de-convivio-profissional-para-devs",
        "title": "Regras de conv\u00edvio profissional [Para Devs]",
        "status": "published",
        "type": "content",
        "source_url": null,
        "created_at": "2022-11-18T14:42:04.414Z",
        "updated_at": "2022-11-18T14:42:24.836Z",
        "published_at": "2022-11-18T14:42:04.449Z",
        "deleted_at": null,
        "owner_username": "ramonpenteado",
        "tabcoins": 8,
        "tabcoins_credit": 7,
        "tabcoins_debit": 0,
        "children_deep_count": 10
    },
    {
        "id": "2b8937b7-a356-4837-acc7-6372c9c491c4",
        "owner_id": "110cc974-4c56-4074-afbc-81ce22aa6013",
        "parent_id": null,
        "slug": "hacker-prodigio-george-hotz-fara-estagio-temporario-no-twitter",
        "title": "Hacker prod\u00edgio George Hotz far\u00e1 est\u00e1gio tempor\u00e1rio no Twitter",
        "status": "published",
        "type": "content",
        "source_url": "https://news.ycombinator.com/item?id=33649326",
        "created_at": "2022-11-18T14:25:58.370Z",
        "updated_at": "2022-11-18T14:25:58.370Z",
        "published_at": "2022-11-18T14:25:58.392Z",
        "deleted_at": null,
        "owner_username": "gugadeschamps",
        "tabcoins": 2,
        "tabcoins_credit": 1,
        "tabcoins_debit": 0,
        "children_deep_count": 0
    },
    {
        "id": "4886f0c6-d08b-4ae6-a6a5-1ab80df39992",
        "owner_id": "b796d561-e9ab-46d9-8bf6-251be36e96e5",
        "parent_id": null,
        "slug": "times-estao-se-demetindo-do-twitter",
        "title": "times estao se demetindo do twitter",
        "status": "published",
        "type": "content",
        "source_url": "https://www.tecmundo.com.br/redes-sociais/254542-rip-twitter-funcionarios-deixam-empresa-elon-musk.htm",
        "created_at": "2022-11-18T07:31:07.271Z",
        "updated_at": "2022-11-18T07:31:07.271Z",
        "published_at": "2022-11-18T07:31:07.290Z",
        "deleted_at": null,
        "owner_username": "CarlosZiegler",
        "tabcoins": -2,
        "tabcoins_credit": 0,
        "tabcoins_debit": -3,
        "children_deep_count": 2
    },
    {
        "id": "09aef1f1-c191-4bbe-a300-da845ae0c777",
        "owner_id": "07ea33ea-78bd-4578-bad2-1cf5323cab07",
        "parent_id": null,
        "slug": "gerador-de-cartao-de-visita-do-github",
        "title": "Gerador de cart\u00e3o de visita do GitHub",
        "status": "published",
        "type": "content",
        "source_url": null,
        "created_at": "2022-11-18T00:25:01.835Z",
        "updated_at": "2022-11-18T00:25:01.835Z",
        "published_at": "2022-11-18T00:25:01.857Z",
        "deleted_at": null,
        "owner_username": "filipedeschamps",
        "tabcoins": 12,
        "tabcoins_credit": 11,
        "tabcoins_debit": 0,
        "children_deep_count": 13
    },
    {
        "id": "43f29667-5ea7-4dbe-8a44-d3d6b922763e",
        "owner_id": "110cc974-4c56-4074-afbc-81ce22aa6013",
        "parent_id": null,
        "slug": "tudo-o-que-voce-precisa-para-fazer-um-website-e-html",
        "title": "Tudo o que voc\u00ea precisa para fazer um website \u00e9 HTML",
        "status": "published",
        "type": "content",
        "source_url": "https://whitep4nth3r.com/blog/html-is-all-you-need-to-make-a-website/",
        "created_at": "2022-11-17T23:30:01.698Z",
        "updated_at": "2022-11-18T00:00:26.188Z",
        "published_at": "2022-11-17T23:30:01.717Z",
        "deleted_at": null,
        "owner_username": "gugadeschamps",
        "tabcoins": 7,
        "tabcoins_credit": 7,
        "tabcoins_debit": -1,
        "children_deep_count": 4
    },
    {
        "id": "62e52828-5f87-48aa-9a8c-11f17292c635",
        "owner_id": "a634b01a-53ec-4b3d-9c7c-da7e84b36e79",
        "parent_id": null,
        "slug": "cursos-da-amazon-gratuitos-e-com-certificacao",
        "title": "Mais de 100 Cursos da Amazon Gratuitos e Com Certifica\u00e7\u00e3o",
        "status": "published",
        "type": "content",
        "source_url": null,
        "created_at": "2022-11-17T20:55:42.147Z",
        "updated_at": "2022-11-17T21:14:43.177Z",
        "published_at": "2022-11-17T20:55:42.167Z",
        "deleted_at": null,
        "owner_username": "GabrielSozinho",
        "tabcoins": 10,
        "tabcoins_credit": 9,
        "tabcoins_debit": 0,
        "children_deep_count": 13
    },
    {
        "id": "41dabe1a-94b7-44fa-a6d1-ee3c89a36f9f",
        "owner_id": "f21f2950-7d7d-45cd-93f2-edbb6165e6cd",
        "parent_id": null,
        "slug": "governo-de-tuvalu-decide-criar-uma-copia-do-pais-arquipelago-no-metaverso-em-meio-a-ameaca-de-desaparecimento-por-conta-das-mudancas-climaticas",
        "title": "Governo de Tuvalu decide criar uma c\u00f3pia do pa\u00eds-arquip\u00e9lago no metaverso, em meio \u00e0 amea\u00e7a de desaparecimento por conta das mudan\u00e7as clim\u00e1ticas",
        "status": "published",
        "type": "content",
        "source_url": "https://canaltech.com.br/internet/pais-esta-sendo-reconstruido-no-metaverso-para-fugir-das-mudancas-climaticas-229829/",
        "created_at": "2022-11-17T20:45:02.106Z",
        "updated_at": "2022-11-17T20:45:02.106Z",
        "published_at": "2022-11-17T20:45:02.128Z",
        "deleted_at": null,
        "owner_username": "FlaviaCarvalho",
        "tabcoins": 3,
        "tabcoins_credit": 2,
        "tabcoins_debit": 0,
        "children_deep_count": 0
    },
    {
        "id": "8d6d71d5-61d6-46da-8679-49cf2c8345d4",
        "owner_id": "f21f2950-7d7d-45cd-93f2-edbb6165e6cd",
        "parent_id": null,
        "slug": "estao-abertas-as-inscricoes-para-o-hackathon-web3-tokenizacao-do-patrimonio-da-uniao-com-150-mil-reais-em-premios",
        "title": "Est\u00e3o abertas as inscri\u00e7\u00f5es para o \u201cHackathon Web3: Tokeniza\u00e7\u00e3o do Patrim\u00f4nio da Uni\u00e3o\u201d, com 150 mil reais em pr\u00eamios",
        "status": "published",
        "type": "content",
        "source_url": "https://www.convergenciadigital.com.br/Carreira/Serpro-promove-Hackathon-Web3-para-tokenizacao-do-Patrimonio-da-Uniao-61963.html#.Y3aGCXbMK5c",
        "created_at": "2022-11-17T20:00:17.800Z",
        "updated_at": "2022-11-17T20:00:17.800Z",
        "published_at": "2022-11-17T20:00:17.826Z",
        "deleted_at": null,
        "owner_username": "FlaviaCarvalho",
        "tabcoins": 1,
        "tabcoins_credit": 0,
        "tabcoins_debit": 0,
        "children_deep_count": 1
    },
    {
        "id": "53a04549-84a2-440b-8645-3ceefb93be32",
        "owner_id": "b796d561-e9ab-46d9-8bf6-251be36e96e5",
        "parent_id": null,
        "slug": "modernizacao-eficaz-de-sistemas-de-software-legados",
        "title": "Moderniza\u00e7\u00e3o eficaz de sistemas de software legados",
        "status": "published",
        "type": "content",
        "source_url": "https://martinfowler.com/articles/patterns-legacy-displacement/",
        "created_at": "2022-11-17T19:59:45.973Z",
        "updated_at": "2022-11-17T19:59:45.973Z",
        "published_at": "2022-11-17T19:59:45.999Z",
        "deleted_at": null,
        "owner_username": "CarlosZiegler",
        "tabcoins": 8,
        "tabcoins_credit": 7,
        "tabcoins_debit": 0,
        "children_deep_count": 2
    },
    {
        "id": "a059481a-5c1f-40fb-b5ff-bba547ef8555",
        "owner_id": "f21f2950-7d7d-45cd-93f2-edbb6165e6cd",
        "parent_id": null,
        "slug": "tiktok-comeca-a-testar-versao-inicial-de-sua-api-de-pesquisa-que-visa-melhorar-o-acesso-a-dados-sobre-conteudo-e-atividades-no-aplicativo",
        "title": "TikTok come\u00e7a a testar vers\u00e3o inicial de sua API de pesquisa, que visa melhorar o acesso a dados sobre conte\u00fado e atividades no aplicativo",
        "status": "published",
        "type": "content",
        "source_url": "https://techcrunch.com/2022/11/17/tiktok-testing-early-version-platform-research-api/",
        "created_at": "2022-11-17T19:00:14.861Z",
        "updated_at": "2022-11-17T19:00:14.861Z",
        "published_at": "2022-11-17T19:00:14.888Z",
        "deleted_at": null,
        "owner_username": "FlaviaCarvalho",
        "tabcoins": 3,
        "tabcoins_credit": 2,
        "tabcoins_debit": 0,
        "children_deep_count": 0
    },
    {
        "id": "425f2f3d-b31e-44fa-9f1c-7379170ed06a",
        "owner_id": "74346400-b526-4e32-bcb9-71433b01e0a4",
        "parent_id": null,
        "slug": "estrategia-de-sites-escravos-para-micro-saas-seo",
        "title": "Estrat\u00e9gia de SEO para Micro-SaaS (SEO)",
        "status": "published",
        "type": "content",
        "source_url": "https://microsaas.substack.com/p/estrategias-de-seo-para-micro-saas",
        "created_at": "2022-11-17T17:06:28.738Z",
        "updated_at": "2022-11-17T20:48:40.452Z",
        "published_at": "2022-11-17T17:06:28.756Z",
        "deleted_at": null,
        "owner_username": "bokamoto",
        "tabcoins": 3,
        "tabcoins_credit": 4,
        "tabcoins_debit": -2,
        "children_deep_count": 2
    },
    {
        "id": "df9a0925-a43c-496e-b864-71a152970c32",
        "owner_id": "32b05cea-ef18-4ded-bc7c-1457897f3f58",
        "parent_id": null,
        "slug": "criando-aliases-para-comandos-no-terminal",
        "title": "Criando aliases para comandos no terminal",
        "status": "published",
        "type": "content",
        "source_url": null,
        "created_at": "2022-11-17T15:47:39.608Z",
        "updated_at": "2022-11-17T15:47:39.608Z",
        "published_at": "2022-11-17T15:47:39.631Z",
        "deleted_at": null,
        "owner_username": "francine",
        "tabcoins": 10,
        "tabcoins_credit": 9,
        "tabcoins_debit": 0,
        "children_deep_count": 12
    },
    {
        "id": "f93a5f69-d76e-4a8f-9b1a-962509db852b",
        "owner_id": "101cc72f-04df-479b-9b02-67cb92ddc3d9",
        "parent_id": null,
        "slug": "segue-a-lista-de-comandos-docker-e-sua-utilidade",
        "title": "Segue a lista de comandos docker e sua utilidade:",
        "status": "published",
        "type": "content",
        "source_url": null,
        "created_at": "2022-11-17T15:12:38.518Z",
        "updated_at": "2022-11-17T15:12:38.518Z",
        "published_at": "2022-11-17T15:12:38.546Z",
        "deleted_at": null,
        "owner_username": "leomoreiradev",
        "tabcoins": 3,
        "tabcoins_credit": 2,
        "tabcoins_debit": 0,
        "children_deep_count": 1
    },
    {
        "id": "a3f0952c-5213-433e-85eb-7051dbc8fdce",
        "owner_id": "f21f2950-7d7d-45cd-93f2-edbb6165e6cd",
        "parent_id": null,
        "slug": "qualcomm-apresenta-nova-cpu-oryon-para-competir-com-os-processadores-m1-e-m2-da-apple",
        "title": "Qualcomm apresenta nova CPU Oryon para competir com os processadores M1 e M2 da Apple",
        "status": "published",
        "type": "content",
        "source_url": "https://www.theregister.com/2022/11/17/qualcomm_nuvia_arm/",
        "created_at": "2022-11-17T14:15:15.519Z",
        "updated_at": "2022-11-17T14:15:15.519Z",
        "published_at": "2022-11-17T14:15:15.584Z",
        "deleted_at": null,
        "owner_username": "FlaviaCarvalho",
        "tabcoins": 2,
        "tabcoins_credit": 1,
        "tabcoins_debit": 0,
        "children_deep_count": 0
    },
    {
        "id": "78ff24f6-fbea-4dfb-bf67-01e211db7400",
        "owner_id": "f21f2950-7d7d-45cd-93f2-edbb6165e6cd",
        "parent_id": null,
        "slug": "engenheiros-da-holanda-desenvolvem-supergps-que-substitui-satelites-por-torres-de-radio-para-rastreamento-com-precisao-de-centimetros",
        "title": "Engenheiros da Holanda desenvolvem \"SuperGPS\" que substitui sat\u00e9lites por torres de r\u00e1dio para rastreamento com precis\u00e3o de cent\u00edmetros",
        "status": "published",
        "type": "content",
        "source_url": "https://newatlas.com/telecommunications/supergps-radio-centimeter-location-tracking/",
        "created_at": "2022-11-17T14:13:44.412Z",
        "updated_at": "2022-11-17T14:13:44.412Z",
        "published_at": "2022-11-17T14:13:44.437Z",
        "deleted_at": null,
        "owner_username": "FlaviaCarvalho",
        "tabcoins": 1,
        "tabcoins_credit": 1,
        "tabcoins_debit": -1,
        "children_deep_count": 0
    },
    {
        "id": "bea26af4-ebf6-4018-81e9-fca611e94e83",
        "owner_id": "f21f2950-7d7d-45cd-93f2-edbb6165e6cd",
        "parent_id": null,
        "slug": "pegaso-da-petrobras-e-considerado-o-maior-e-mais-ecoeficiente-supercomputador-da-america-latina",
        "title": "P\u00e9gaso, da Petrobras, \u00e9 considerado o maior e mais ecoeficiente supercomputador da Am\u00e9rica Latina",
        "status": "published",
        "type": "content",
        "source_url": "https://www.agenciapetrobras.com.br/Materia/ExibirMateria?p_materia=985601",
        "created_at": "2022-11-17T14:12:25.955Z",
        "updated_at": "2022-11-17T14:12:25.955Z",
        "published_at": "2022-11-17T14:12:25.980Z",
        "deleted_at": null,
        "owner_username": "FlaviaCarvalho",
        "tabcoins": 1,
        "tabcoins_credit": 0,
        "tabcoins_debit": 0,
        "children_deep_count": 0
    },
    {
        "id": "547f743d-00e9-48c2-ad30-175af4693a34",
        "owner_id": "f21f2950-7d7d-45cd-93f2-edbb6165e6cd",
        "parent_id": null,
        "slug": "nvidia-e-microsoft-anunciam-parceria-para-construir-um-dos-supercomputadores-de-ia-mais-poderosos-do-mundo",
        "title": "Nvidia e Microsoft anunciam parceria para construir um dos supercomputadores de IA mais poderosos do mundo",
        "status": "published",
        "type": "content",
        "source_url": "https://www.theverge.com/2022/11/17/23464001/nvidia-microsoft-ai-supercomputer-announcement",
        "created_at": "2022-11-17T14:05:11.269Z",
        "updated_at": "2022-11-17T14:05:11.269Z",
        "published_at": "2022-11-17T14:05:11.296Z",
        "deleted_at": null,
        "owner_username": "FlaviaCarvalho",
        "tabcoins": 1,
        "tabcoins_credit": 0,
        "tabcoins_debit": 0,
        "children_deep_count": 0
    },
    {
        "id": "391784db-5f6e-424d-9773-e028154673af",
        "owner_id": "f21f2950-7d7d-45cd-93f2-edbb6165e6cd",
        "parent_id": null,
        "slug": "bolsa-de-valores-australiana-interrompe-projeto-que-visava-substituir-plataforma-de-negociacao-de-acoes-por-sistema-baseado-em-blockchain",
        "title": "Bolsa de valores australiana interrompe projeto que visava substituir plataforma de negocia\u00e7\u00e3o de a\u00e7\u00f5es por sistema baseado em blockchain",
        "status": "published",
        "type": "content",
        "source_url": "https://www.theregister.com/2022/11/17/asx_blockchain_reading_project_paused/",
        "created_at": "2022-11-17T14:02:38.256Z",
        "updated_at": "2022-11-17T14:02:38.256Z",
        "published_at": "2022-11-17T14:02:38.274Z",
        "deleted_at": null,
        "owner_username": "FlaviaCarvalho",
        "tabcoins": 1,
        "tabcoins_credit": 0,
        "tabcoins_debit": 0,
        "children_deep_count": 3
    },
    {
        "id": "a5d23ec5-0167-4bd3-a48d-ddb33da9dab0",
        "owner_id": "110cc974-4c56-4074-afbc-81ce22aa6013",
        "parent_id": null,
        "slug": "startup-usa-ia-e-visao-computacional-de-um-jeito-fantastico-na-agricultura",
        "title": "Startup usa IA e vis\u00e3o computacional de um jeito fant\u00e1stico na agricultura",
        "status": "published",
        "type": "content",
        "source_url": "https://www.youtube.com/watch?v=sV0cR_Nhac0",
        "created_at": "2022-11-16T23:36:54.785Z",
        "updated_at": "2022-11-16T23:36:54.785Z",
        "published_at": "2022-11-16T23:36:54.813Z",
        "deleted_at": null,
        "owner_username": "gugadeschamps",
        "tabcoins": 6,
        "tabcoins_credit": 5,
        "tabcoins_debit": 0,
        "children_deep_count": 0
    },
    {
        "id": "d1850549-603e-4fdb-ac59-817ea6d7edbe",
        "owner_id": "07ea33ea-78bd-4578-bad2-1cf5323cab07",
        "parent_id": null,
        "slug": "email-vazado-de-elon-musk-revela-6-regras-para-uma-produtividade-insana",
        "title": "Email vazado de Elon Musk revela 6 regras para uma alta produtividade",
        "status": "published",
        "type": "content",
        "source_url": "https://twitter.com/LiamKircher/status/1592866981145104385",
        "created_at": "2022-11-16T23:20:58.252Z",
        "updated_at": "2022-11-22T22:26:42.354Z",
        "published_at": "2022-11-16T23:20:58.263Z",
        "deleted_at": null,
        "owner_username": "filipedeschamps",
        "tabcoins": 31,
        "tabcoins_credit": 30,
        "tabcoins_debit": 0,
        "children_deep_count": 23
    },
    {
        "id": "cc2668e7-de06-47d8-ad9e-10b79526ae4f",
        "owner_id": "f21f2950-7d7d-45cd-93f2-edbb6165e6cd",
        "parent_id": null,
        "slug": "codigo-fonte-do-twitter-revela-esforcos-para-adicionar-criptografia-de-ponta-a-ponta-a-mensagens-diretas",
        "title": "C\u00f3digo-fonte do Twitter revela esfor\u00e7os para adicionar criptografia de ponta a ponta a mensagens diretas",
        "status": "published",
        "type": "content",
        "source_url": "https://www.bleepingcomputer.com/news/security/twitter-source-code-indicates-end-to-end-encrypted-dms-are-coming/",
        "created_at": "2022-11-16T22:35:03.157Z",
        "updated_at": "2022-11-16T22:35:03.157Z",
        "published_at": "2022-11-16T22:35:03.184Z",
        "deleted_at": null,
        "owner_username": "FlaviaCarvalho",
        "tabcoins": 2,
        "tabcoins_credit": 1,
        "tabcoins_debit": 0,
        "children_deep_count": 0
    },
    {
        "id": "e1aea63f-dfc1-4ad2-bbaf-030451aab5d0",
        "owner_id": "f21f2950-7d7d-45cd-93f2-edbb6165e6cd",
        "parent_id": null,
        "slug": "recurso-app-tracking-protection-do-duckduckgo-para-android-chega-a-fase-open-beta",
        "title": "Ferramenta anti-rastreamento do DuckDuckGo chega ao Android com a promessa de ser ainda mais eficiente que o App Tracking Transparency da Apple",
        "status": "published",
        "type": "content",
        "source_url": "https://www.bleepingcomputer.com/news/security/duckduckgo-now-lets-all-android-users-block-trackers-in-their-apps/",
        "created_at": "2022-11-16T22:10:41.385Z",
        "updated_at": "2022-11-17T14:21:12.762Z",
        "published_at": "2022-11-16T22:10:41.394Z",
        "deleted_at": null,
        "owner_username": "FlaviaCarvalho",
        "tabcoins": 5,
        "tabcoins_credit": 5,
        "tabcoins_debit": -1,
        "children_deep_count": 1
    },
    {
        "id": "cfa3bd33-5fb6-4bb5-86ba-0957765e3f4c",
        "owner_id": "f21f2950-7d7d-45cd-93f2-edbb6165e6cd",
        "parent_id": null,
        "slug": "plataforma-notion-testa-novo-recurso-de-geracao-de-texto-por-ia",
        "title": "Plataforma Notion testa novo recurso de gera\u00e7\u00e3o de texto por IA",
        "status": "published",
        "type": "content",
        "source_url": "https://www.theverge.com/2022/11/16/23460904/notion-ai-notes-writing-machine-learning",
        "created_at": "2022-11-16T21:41:19.082Z",
        "updated_at": "2022-11-16T21:41:19.082Z",
        "published_at": "2022-11-16T21:41:19.109Z",
        "deleted_at": null,
        "owner_username": "FlaviaCarvalho",
        "tabcoins": 4,
        "tabcoins_credit": 3,
        "tabcoins_debit": 0,
        "children_deep_count": 0
    },
    {
        "id": "d0979685-b9d0-42a1-8aca-6439c8f80058",
        "owner_id": "f21f2950-7d7d-45cd-93f2-edbb6165e6cd",
        "parent_id": null,
        "slug": "analise-de-ia-sugere-que-dinossauro-predador-por-tras-das-grandes-pegadas-do-lark-quarry-conservation-park-na-australia-pode-ter-sido-um-herbivoro",
        "title": "An\u00e1lise de IA sugere que dinossauro \u201cpredador\u201d por tr\u00e1s das grandes pegadas do Lark Quarry Conservation Park, na Austr\u00e1lia, pode ter sido um herb\u00edvoro",
        "status": "published",
        "type": "content",
        "source_url": "https://www.theregister.com/2022/11/16/ancient_dinosaur_tracks_analysed_using/",
        "created_at": "2022-11-16T20:30:47.547Z",
        "updated_at": "2022-11-16T20:30:47.547Z",
        "published_at": "2022-11-16T20:30:47.567Z",
        "deleted_at": null,
        "owner_username": "FlaviaCarvalho",
        "tabcoins": 3,
        "tabcoins_credit": 2,
        "tabcoins_debit": 0,
        "children_deep_count": 1
    },
    {
        "id": "dd7fd80a-ff93-4857-a9f2-c29f5f33fa0b",
        "owner_id": "a7e17c5b-b415-4326-aada-3e58394a08d0",
        "parent_id": null,
        "slug": "como-criar-uma-api-python-com-fastapi",
        "title": "Como criar uma API Python com FastAPI",
        "status": "published",
        "type": "content",
        "source_url": "https://blog.estevaofay.com/",
        "created_at": "2022-11-16T18:58:30.345Z",
        "updated_at": "2022-11-16T18:58:30.345Z",
        "published_at": "2022-11-16T18:58:30.368Z",
        "deleted_at": null,
        "owner_username": "estevaofay",
        "tabcoins": 3,
        "tabcoins_credit": 2,
        "tabcoins_debit": 0,
        "children_deep_count": 0
    },
    {
        "id": "657d3f1e-b163-4677-9bb4-b0b278f83d3b",
        "owner_id": "d5354f62-f783-4d9a-bf15-651c10a01445",
        "parent_id": null,
        "slug": "please-suggest-the-project-for-college",
        "title": "Please Suggest the Project for College",
        "status": "published",
        "type": "content",
        "source_url": null,
        "created_at": "2022-11-16T17:43:08.433Z",
        "updated_at": "2022-11-16T17:43:08.433Z",
        "published_at": "2022-11-16T17:43:08.452Z",
        "deleted_at": null,
        "owner_username": "gulshannegi",
        "tabcoins": -3,
        "tabcoins_credit": 1,
        "tabcoins_debit": -5,
        "children_deep_count": 4
    },
    {
        "id": "16e3ee55-baee-4a13-aa16-db5644ae9e11",
        "owner_id": "6803d49e-b744-4102-8f7e-c28a4b770adc",
        "parent_id": null,
        "slug": "como-https-funciona",
        "title": "Como HTTPS funciona",
        "status": "published",
        "type": "content",
        "source_url": "https://howhttps.works/",
        "created_at": "2022-11-16T14:46:03.759Z",
        "updated_at": "2022-11-16T14:46:03.759Z",
        "published_at": "2022-11-16T14:46:03.778Z",
        "deleted_at": null,
        "owner_username": "Luisa",
        "tabcoins": 11,
        "tabcoins_credit": 10,
        "tabcoins_debit": 0,
        "children_deep_count": 8
    },
    {
        "id": "5d5cb942-7ae9-4770-b1b4-6a3dc1b085f6",
        "owner_id": "f21f2950-7d7d-45cd-93f2-edbb6165e6cd",
        "parent_id": null,
        "slug": "lancamento-da-primeira-missao-artemis-e-bem-sucedido-e-capsula-orion-ja-esta-em-direcao-a-lua",
        "title": "Lan\u00e7amento da primeira miss\u00e3o Artemis \u00e9 bem-sucedido e c\u00e1psula Orion j\u00e1 est\u00e1 em dire\u00e7\u00e3o \u00e0 Lua",
        "status": "published",
        "type": "content",
        "source_url": "https://www.space.com/nasa-artemis-1-moon-mission-launch",
        "created_at": "2022-11-16T14:26:46.692Z",
        "updated_at": "2022-11-16T14:26:46.692Z",
        "published_at": "2022-11-16T14:26:46.711Z",
        "deleted_at": null,
        "owner_username": "FlaviaCarvalho",
        "tabcoins": 2,
        "tabcoins_credit": 1,
        "tabcoins_debit": 0,
        "children_deep_count": 1
    },
    {
        "id": "55c98f55-dd8a-4e08-9828-20ace3f9113f",
        "owner_id": "f21f2950-7d7d-45cd-93f2-edbb6165e6cd",
        "parent_id": null,
        "slug": "meta-lanca-novo-modelo-de-linguagem-open-source-com-capacidade-de-compreender-raciocinios-cientificos",
        "title": "Meta lan\u00e7a novo modelo de linguagem open source com capacidade de compreender racioc\u00ednios cient\u00edficos",
        "status": "published",
        "type": "content",
        "source_url": "https://wandb.ai/telidavies/ml-news/reports/Galactica-Open-Source-120B-Param-Scientific-Language-Model-By-Papers-with-Code-Meta-AI--VmlldzoyOTc3MDM2",
        "created_at": "2022-11-16T14:15:55.805Z",
        "updated_at": "2022-11-16T14:15:55.805Z",
        "published_at": "2022-11-16T14:15:55.825Z",
        "deleted_at": null,
        "owner_username": "FlaviaCarvalho",
        "tabcoins": 2,
        "tabcoins_credit": 1,
        "tabcoins_debit": 0,
        "children_deep_count": 0
    },
    {
        "id": "baa366bf-777e-40a4-b7e2-7685a3e9f18e",
        "owner_id": "f21f2950-7d7d-45cd-93f2-edbb6165e6cd",
        "parent_id": null,
        "slug": "deno-1-28-adiciona-suporte-oficial-a-modulos-npm",
        "title": "Deno 1.28 adiciona suporte oficial a m\u00f3dulos npm",
        "status": "published",
        "type": "content",
        "source_url": "https://deno.com/blog/v1.28",
        "created_at": "2022-11-16T14:10:51.346Z",
        "updated_at": "2022-11-16T14:10:51.346Z",
        "published_at": "2022-11-16T14:10:51.382Z",
        "deleted_at": null,
        "owner_username": "FlaviaCarvalho",
        "tabcoins": 3,
        "tabcoins_credit": 2,
        "tabcoins_debit": 0,
        "children_deep_count": 3
    },
    {
        "id": "11e9f13f-4e5f-4e28-8445-9323c1c4b0dd",
        "owner_id": "f21f2950-7d7d-45cd-93f2-edbb6165e6cd",
        "parent_id": null,
        "slug": "projeto-da-linux-foundation-europe-visa-criar-um-framework-de-nuvem-de-telecomunicacoes-de-codigo-aberto",
        "title": "Projeto da Linux Foundation Europe visa criar um framework de nuvem de telecomunica\u00e7\u00f5es de c\u00f3digo aberto",
        "status": "published",
        "type": "content",
        "source_url": "https://techcrunch.com/2022/11/15/lf-europes-project-sylva-wants-to-create-an-open-source-telco-cloud-stack/",
        "created_at": "2022-11-15T22:47:17.068Z",
        "updated_at": "2022-11-15T22:47:17.068Z",
        "published_at": "2022-11-15T22:47:17.094Z",
        "deleted_at": null,
        "owner_username": "FlaviaCarvalho",
        "tabcoins": 3,
        "tabcoins_credit": 2,
        "tabcoins_debit": 0,
        "children_deep_count": 0
    },
    {
        "id": "c72c49ce-a28a-4679-ac44-a2c7697ea08d",
        "owner_id": "f21f2950-7d7d-45cd-93f2-edbb6165e6cd",
        "parent_id": null,
        "slug": "pesquisadores-exploram-vulnerabilidade-do-protocolo-tte-para-quebrar-garantias-de-seguranca-da-rede-usada-em-espaconaves",
        "title": "Pesquisadores exploram vulnerabilidade do protocolo TTE para quebrar garantias de seguran\u00e7a da rede usada em espa\u00e7onaves",
        "status": "published",
        "type": "content",
        "source_url": "https://arstechnica.com/information-technology/2022/11/researchers-break-security-guarantees-of-tte-networking-used-in-spacecraft/",
        "created_at": "2022-11-15T22:05:07.547Z",
        "updated_at": "2022-11-15T22:05:07.547Z",
        "published_at": "2022-11-15T22:05:07.585Z",
        "deleted_at": null,
        "owner_username": "FlaviaCarvalho",
        "tabcoins": 3,
        "tabcoins_credit": 2,
        "tabcoins_debit": 0,
        "children_deep_count": 0
    },
    {
        "id": "3cfe5d71-00ed-4084-bed5-b2f6c86dd254",
        "owner_id": "f21f2950-7d7d-45cd-93f2-edbb6165e6cd",
        "parent_id": null,
        "slug": "rimac-nevera-atinge-412-km-h-e-se-torna-o-carro-eletrico-mais-rapido-do-mundo",
        "title": "Rimac Nevera atinge 412 km/h e se torna o carro el\u00e9trico mais r\u00e1pido do mundo",
        "status": "published",
        "type": "content",
        "source_url": "https://www.rimac-automobili.com/media/press-releases/record-breaking-rimac-nevera-hits-412kph-to-become-worlds-fastest-production-electric-car/",
        "created_at": "2022-11-15T18:53:12.905Z",
        "updated_at": "2022-11-16T17:56:37.154Z",
        "published_at": "2022-11-15T18:53:12.929Z",
        "deleted_at": null,
        "owner_username": "FlaviaCarvalho",
        "tabcoins": 2,
        "tabcoins_credit": 1,
        "tabcoins_debit": 0,
        "children_deep_count": 6
    },
    {
        "id": "f68ba55c-a331-4a80-9df1-756f8b19534b",
        "owner_id": "88480bef-5da9-4290-ad70-f607c12c93c2",
        "parent_id": null,
        "slug": "pontos-importantes-para-uma-entrevista-de-emprego-no-exterior",
        "title": "Pontos importantes para uma entrevista de emprego no exterior",
        "status": "published",
        "type": "content",
        "source_url": null,
        "created_at": "2022-11-15T18:14:30.141Z",
        "updated_at": "2022-11-15T18:14:30.141Z",
        "published_at": "2022-11-15T18:14:30.165Z",
        "deleted_at": null,
        "owner_username": "ramonpenteado",
        "tabcoins": 20,
        "tabcoins_credit": 19,
        "tabcoins_debit": 0,
        "children_deep_count": 15
    },
    {
        "id": "0a7bbb54-98fa-493d-bf84-d833c4f170fd",
        "owner_id": "07ea33ea-78bd-4578-bad2-1cf5323cab07",
        "parent_id": null,
        "slug": "planetscale-anuncia-feature-que-deixa-queries-pesadas-ate-1-000-vezes-mais-rapidas",
        "title": "PlanetScale anuncia feature que deixa Queries pesadas at\u00e9 1.000 vezes mais r\u00e1pidas",
        "status": "published",
        "type": "content",
        "source_url": "https://planetscale.com/blog/introducing-planetscale-boost",
        "created_at": "2022-11-15T17:52:57.232Z",
        "updated_at": "2022-11-15T17:52:57.232Z",
        "published_at": "2022-11-15T17:52:57.265Z",
        "deleted_at": null,
        "owner_username": "filipedeschamps",
        "tabcoins": 10,
        "tabcoins_credit": 9,
        "tabcoins_debit": 0,
        "children_deep_count": 2
    },
    {
        "id": "5e5640b8-9459-4d19-b9c2-d16cd7bdcb79",
        "owner_id": "f21f2950-7d7d-45cd-93f2-edbb6165e6cd",
        "parent_id": null,
        "slug": "ais-estao-dando-poderes-divinos-as-seguradoras-diz-chefe-de-uma-das-maiores-companhias-de-seguros-do-japao",
        "title": "IAs est\u00e3o dando \"poderes divinos\" \u00e0s seguradoras, diz chefe de uma das maiores companhias de seguros do Jap\u00e3o",
        "status": "published",
        "type": "content",
        "source_url": "https://archive.ph/s7XLE",
        "created_at": "2022-11-15T16:37:15.935Z",
        "updated_at": "2022-11-15T19:24:53.816Z",
        "published_at": "2022-11-15T16:37:15.975Z",
        "deleted_at": null,
        "owner_username": "FlaviaCarvalho",
        "tabcoins": 1,
        "tabcoins_credit": 0,
        "tabcoins_debit": 0,
        "children_deep_count": 0
    },
    {
        "id": "708dc1c2-d9ab-4293-b38e-086b24e6cbf7",
        "owner_id": "f21f2950-7d7d-45cd-93f2-edbb6165e6cd",
        "parent_id": null,
        "slug": "github-agora-permite-reportar-vulnerabilidades-em-repositorios-publicos-de-forma-privada",
        "title": "GitHub agora permite reportar vulnerabilidades em reposit\u00f3rios p\u00fablicos de forma privada",
        "status": "published",
        "type": "content",
        "source_url": "https://www.theregister.com/2022/11/14/github_private_vulnerability_reporting/",
        "created_at": "2022-11-15T16:35:49.852Z",
        "updated_at": "2022-11-15T16:35:49.852Z",
        "published_at": "2022-11-15T16:35:49.905Z",
        "deleted_at": null,
        "owner_username": "FlaviaCarvalho",
        "tabcoins": 4,
        "tabcoins_credit": 3,
        "tabcoins_debit": 0,
        "children_deep_count": 1
    },
    {
        "id": "58a582cb-c9f5-4008-93e9-82f73d581cae",
        "owner_id": "f21f2950-7d7d-45cd-93f2-edbb6165e6cd",
        "parent_id": null,
        "slug": "startup-de-taxis-autonomos-waymo-usa-seus-veiculos-para-criar-mapas-meteorologicos-em-tempo-real",
        "title": "Startup de t\u00e1xis aut\u00f4nomos Waymo usa seus ve\u00edculos para criar mapas meteorol\u00f3gicos em tempo real",
        "status": "published",
        "type": "content",
        "source_url": "https://blog.waymo.com/2022/11/using-cutting-edge-weather-research-to-advance-the-Waymo-Driver.html",
        "created_at": "2022-11-15T16:34:23.162Z",
        "updated_at": "2022-11-15T16:34:23.162Z",
        "published_at": "2022-11-15T16:34:23.325Z",
        "deleted_at": null,
        "owner_username": "FlaviaCarvalho",
        "tabcoins": 3,
        "tabcoins_credit": 2,
        "tabcoins_debit": 0,
        "children_deep_count": 0
    },
    {
        "id": "39be13e4-1248-407b-a750-2463852727d6",
        "owner_id": "b796d561-e9ab-46d9-8bf6-251be36e96e5",
        "parent_id": null,
        "slug": "ide-para-qa",
        "title": "IDE para QA",
        "status": "published",
        "type": "content",
        "source_url": "https://www.jetbrains.com/pt-br/aqua/",
        "created_at": "2022-11-15T15:35:34.015Z",
        "updated_at": "2022-11-15T15:35:45.376Z",
        "published_at": "2022-11-15T15:35:34.035Z",
        "deleted_at": null,
        "owner_username": "CarlosZiegler",
        "tabcoins": 10,
        "tabcoins_credit": 9,
        "tabcoins_debit": 0,
        "children_deep_count": 3
    },
    {
        "id": "18b602ac-bdbb-4686-9e6c-d578ee585392",
        "owner_id": "67fe21e8-ec0e-44fa-9c06-29966a05dbce",
        "parent_id": null,
        "slug": "twitter-demite-mais-4-mil-funcionarios-em-nova-rodada-de-cortes",
        "title": "Twitter demite mais 4 mil funcion\u00e1rios em nova rodada de cortes",
        "status": "published",
        "type": "content",
        "source_url": "https://www.tecmundo.com.br/mercado/254357-twitter-demite-4-mil-funcionarios-nova-rodada-cortes.htm",
        "created_at": "2022-11-15T15:29:58.738Z",
        "updated_at": "2022-11-15T15:30:30.574Z",
        "published_at": "2022-11-15T15:29:58.765Z",
        "deleted_at": null,
        "owner_username": "aleatorio39",
        "tabcoins": 4,
        "tabcoins_credit": 6,
        "tabcoins_debit": -3,
        "children_deep_count": 1
    },
    {
        "id": "5c5bfb2a-b6a4-4a04-9714-356958bdeecd",
        "owner_id": "1ec24a85-6f44-4d18-a483-27f24d401cfc",
        "parent_id": null,
        "slug": "instalando-elixir-e-erlang-no-linux-com-asdf",
        "title": "Instalando Elixir e Erlang no Linux com asdf",
        "status": "published",
        "type": "content",
        "source_url": null,
        "created_at": "2022-11-15T09:35:24.500Z",
        "updated_at": "2022-11-15T09:35:24.500Z",
        "published_at": "2022-11-15T09:35:24.532Z",
        "deleted_at": null,
        "owner_username": "adolfont",
        "tabcoins": 8,
        "tabcoins_credit": 7,
        "tabcoins_debit": 0,
        "children_deep_count": 3
    },
    {
        "id": "3106ae1e-9b2d-46bc-b32e-c1e6c036adf0",
        "owner_id": "95239240-6e12-4a65-a213-aa778c467483",
        "parent_id": null,
        "slug": "arquivo-json-contendo-todos-os-usuarios-do-tabnews-e-algumas-curiosidades",
        "title": "Arquivo JSON contendo todos os usu\u00e1rios do tabnews (E algumas curiosidades)",
        "status": "published",
        "type": "content",
        "source_url": "https://github.com/33gustavo33/tabnews-fetch-all-contents/tree/main",
        "created_at": "2022-11-15T07:02:32.518Z",
        "updated_at": "2022-11-15T19:34:13.102Z",
        "published_at": "2022-11-15T07:02:32.567Z",
        "deleted_at": null,
        "owner_username": "Gustavo33",
        "tabcoins": 21,
        "tabcoins_credit": 20,
        "tabcoins_debit": 0,
        "children_deep_count": 4
    },
    {
        "id": "d0942856-d700-414e-897d-a393851e38e2",
        "owner_id": "ffc1af96-af12-4b8c-a6cf-39ea94dbd9c8",
        "parent_id": null,
        "slug": "reflexoes-sobre-github-copilot-a-terceira-revolucao-computacional",
        "title": "Reflex\u00f5es sobre github copilot - A terceira revolu\u00e7\u00e3o computacional",
        "status": "published",
        "type": "content",
        "source_url": null,
        "created_at": "2022-11-15T04:03:14.481Z",
        "updated_at": "2022-11-15T04:03:14.481Z",
        "published_at": "2022-11-15T04:03:14.535Z",
        "deleted_at": null,
        "owner_username": "samuelhaidu",
        "tabcoins": 15,
        "tabcoins_credit": 15,
        "tabcoins_debit": -1,
        "children_deep_count": 1
    },
    {
        "id": "18581ec7-e990-4bfb-a5a6-41cc943b19d7",
        "owner_id": "c8f6e9b5-3ee1-492c-bf0f-7ac40ccdf99a",
        "parent_id": null,
        "slug": "whatsapp-agora-pode-ser-usado-em-mais-de-um-celular-android",
        "title": "[NEWS] WhatsApp agora pode ser usado em mais de um celular Android",
        "status": "published",
        "type": "content",
        "source_url": "https://www.tecmundo.com.br/software/254316-whatsapp-usado-celular-android.htm",
        "created_at": "2022-11-15T01:14:58.449Z",
        "updated_at": "2024-08-29T17:14:47.309Z",
        "published_at": "2022-11-15T01:14:58.459Z",
        "deleted_at": null,
        "owner_username": "hebertcisco",
        "tabcoins": 9,
        "tabcoins_credit": 8,
        "tabcoins_debit": 0,
        "children_deep_count": 3
    },
    {
        "id": "431a7dc8-00a2-4ed5-af54-f1ccf5f5b29a",
        "owner_id": "c8f6e9b5-3ee1-492c-bf0f-7ac40ccdf99a",
        "parent_id": null,
        "slug": "tiktok-transmitira-copa-do-mundo-em-4k-de-graca-mas-so-na-china",
        "title": "[NEWS] TikTok transmitir\u00e1 Copa do Mundo em 4K de gra\u00e7a, mas s\u00f3 na China",
        "status": "published",
        "type": "content",
        "source_url": "https://www.tecmundo.com.br/redes-sociais/254339-tiktok-transmitira-copa-mundo-4k-graca-so-china.htm",
        "created_at": "2022-11-15T01:10:17.241Z",
        "updated_at": "2022-11-22T12:09:32.073Z",
        "published_at": "2022-11-15T01:10:17.277Z",
        "deleted_at": null,
        "owner_username": "hebertcisco",
        "tabcoins": 6,
        "tabcoins_credit": 5,
        "tabcoins_debit": 0,
        "children_deep_count": 2
    },
    {
        "id": "d00e5f51-4bad-47e1-a8cb-63deac76e233",
        "owner_id": "07ea33ea-78bd-4578-bad2-1cf5323cab07",
        "parent_id": null,
        "slug": "rive-framework-para-animacoes-na-web-e-nativo-melhor-que-flash",
        "title": "Rive: framework para anima\u00e7\u00f5es na Web e Nativo (melhor que Flash)",
        "status": "published",
        "type": "content",
        "source_url": null,
        "created_at": "2022-11-15T00:23:28.707Z",
        "updated_at": "2022-11-15T00:23:28.707Z",
        "published_at": "2022-11-15T00:23:28.739Z",
        "deleted_at": null,
        "owner_username": "filipedeschamps",
        "tabcoins": 11,
        "tabcoins_credit": 10,
        "tabcoins_debit": 0,
        "children_deep_count": 3
    },
    {
        "id": "7c89a6f3-c79c-4c59-99b6-23c743edb1c9",
        "owner_id": "67fe21e8-ec0e-44fa-9c06-29966a05dbce",
        "parent_id": null,
        "slug": "bateria-de-ions-de-zinco-agora-a-base-de-agua",
        "title": "Bateria de \u00edons de zinco agora \u00e0 base de \u00e1gua",
        "status": "published",
        "type": "content",
        "source_url": "https://www.inovacaotecnologica.com.br/noticias/noticia.php?artigo=bateria-ions-zinco-eletrolito-base-agua&id=010115221114#.Y3LMs3aZPIU",
        "created_at": "2022-11-14T23:28:03.092Z",
        "updated_at": "2022-11-14T23:29:17.703Z",
        "published_at": "2022-11-14T23:28:03.130Z",
        "deleted_at": null,
        "owner_username": "aleatorio39",
        "tabcoins": 6,
        "tabcoins_credit": 5,
        "tabcoins_debit": 0,
        "children_deep_count": 2
    },
    {
        "id": "4a0ebaf9-d45e-4acf-95e3-ef733aea11a6",
        "owner_id": "f21f2950-7d7d-45cd-93f2-edbb6165e6cd",
        "parent_id": null,
        "slug": "defesa-civil-lanca-novo-servico-de-compartilhamento-de-alertas-de-desastres-naturais-pelo-whatsapp",
        "title": "Defesa Civil lan\u00e7a novo servi\u00e7o de compartilhamento de alertas de desastres naturais pelo WhatsApp",
        "status": "published",
        "type": "content",
        "source_url": "https://www.tecmundo.com.br/software/254337-brasil-1-pais-divulgar-alertas-desastres-whatsapp.htm",
        "created_at": "2022-11-14T22:44:14.301Z",
        "updated_at": "2022-11-14T22:44:14.301Z",
        "published_at": "2022-11-14T22:44:14.332Z",
        "deleted_at": null,
        "owner_username": "FlaviaCarvalho",
        "tabcoins": 3,
        "tabcoins_credit": 2,
        "tabcoins_debit": 0,
        "children_deep_count": 3
    },
    {
        "id": "4210afb5-9a63-426e-b4e6-b1f64d5aba2e",
        "owner_id": "f21f2950-7d7d-45cd-93f2-edbb6165e6cd",
        "parent_id": null,
        "slug": "jeff-bezos-diz-que-pretende-doar-a-maior-parte-de-sua-fortuna-para-combater-mudancas-climaticas-e-reduzir-a-desigualdade",
        "title": "Jeff Bezos diz que pretende doar a maior parte de sua fortuna para combater mudan\u00e7as clim\u00e1ticas e reduzir a desigualdade",
        "status": "published",
        "type": "content",
        "source_url": "https://www.bbc.com/news/business-63619512",
        "created_at": "2022-11-14T22:17:19.281Z",
        "updated_at": "2022-11-14T22:17:19.281Z",
        "published_at": "2022-11-14T22:17:19.293Z",
        "deleted_at": null,
        "owner_username": "FlaviaCarvalho",
        "tabcoins": 1,
        "tabcoins_credit": 0,
        "tabcoins_debit": 0,
        "children_deep_count": 0
    },
    {
        "id": "caff036c-029d-401c-8720-f43a2af1e24d",
        "owner_id": "f21f2950-7d7d-45cd-93f2-edbb6165e6cd",
        "parent_id": null,
        "slug": "lei-de-resiliencia-cibernetica-da-uniao-europeia-podera-gerar-uma-sobrecarga-de-conformidade-em-desenvolvedores-de-codigo-aberto-alerta-nlnet-labs",
        "title": "Lei de Resili\u00eancia Cibern\u00e9tica da Uni\u00e3o Europeia poder\u00e1 gerar uma sobrecarga de conformidade em desenvolvedores de c\u00f3digo aberto, alerta NLnet Labs",
        "status": "published",
        "type": "content",
        "source_url": "https://blog.nlnetlabs.nl/open-source-software-vs-the-cyber-resilience-act/",
        "created_at": "2022-11-14T21:47:33.466Z",
        "updated_at": "2022-11-14T21:49:01.793Z",
        "published_at": "2022-11-14T21:47:33.500Z",
        "deleted_at": null,
        "owner_username": "FlaviaCarvalho",
        "tabcoins": 2,
        "tabcoins_credit": 1,
        "tabcoins_debit": 0,
        "children_deep_count": 0
    },
    {
        "id": "7efa4af1-90cb-4d94-8c42-3b55b7cf0e86",
        "owner_id": "9cd418e1-b396-4c83-9756-370e295c6767",
        "parent_id": null,
        "slug": "codigo-compilado-vs-interpretado-teste-de-performance",
        "title": "C\u00f3digo Compilado vs Interpretado: teste de performance",
        "status": "published",
        "type": "content",
        "source_url": "https://medium.com/swlh/compiled-vs-interpreted-code-performance-e1a63299760b",
        "created_at": "2022-11-14T18:36:52.234Z",
        "updated_at": "2022-11-14T18:36:52.234Z",
        "published_at": "2022-11-14T18:36:52.270Z",
        "deleted_at": null,
        "owner_username": "wdobeat",
        "tabcoins": 6,
        "tabcoins_credit": 5,
        "tabcoins_debit": 0,
        "children_deep_count": 2
    },
    {
        "id": "e114541b-6f03-45e6-a305-f3c4b8d9b21f",
        "owner_id": "88480bef-5da9-4290-ad70-f607c12c93c2",
        "parent_id": null,
        "slug": "o-que-esperar-de-um-emprego-no-exterior",
        "title": "O que esperar de um emprego no exterior.",
        "status": "published",
        "type": "content",
        "source_url": null,
        "created_at": "2022-11-14T16:42:10.149Z",
        "updated_at": "2022-11-14T16:42:10.149Z",
        "published_at": "2022-11-14T16:42:10.173Z",
        "deleted_at": null,
        "owner_username": "ramonpenteado",
        "tabcoins": 11,
        "tabcoins_credit": 11,
        "tabcoins_debit": -1,
        "children_deep_count": 12
    },
    {
        "id": "c223451b-9b4c-45b9-882e-d2865958519b",
        "owner_id": "110cc974-4c56-4074-afbc-81ce22aa6013",
        "parent_id": null,
        "slug": "os-melhores-dez-minutos-que-voce-vai-perder-hoje",
        "title": "Os melhores dez minutos que voc\u00ea vai perder hoje...",
        "status": "published",
        "type": "content",
        "source_url": "https://www.youtube.com/watch?v=fWDxdoRTZPc",
        "created_at": "2022-11-14T15:18:45.564Z",
        "updated_at": "2022-11-14T15:18:45.564Z",
        "published_at": "2022-11-14T15:18:45.581Z",
        "deleted_at": null,
        "owner_username": "gugadeschamps",
        "tabcoins": 9,
        "tabcoins_credit": 8,
        "tabcoins_debit": 0,
        "children_deep_count": 0
    },
    {
        "id": "6e24727a-0645-4322-92c1-d8b969f421bf",
        "owner_id": "f21f2950-7d7d-45cd-93f2-edbb6165e6cd",
        "parent_id": null,
        "slug": "nova-ui-para-visualizacao-de-codigo-em-repositorios-do-github-substitui-rails-por-react",
        "title": "Nova UI para visualiza\u00e7\u00e3o de c\u00f3digo em reposit\u00f3rios do GitHub substitui Rails por React",
        "status": "published",
        "type": "content",
        "source_url": "https://news.ycombinator.com/item?id=33576722",
        "created_at": "2022-11-14T14:29:17.864Z",
        "updated_at": "2022-11-14T14:29:17.864Z",
        "published_at": "2022-11-14T14:29:17.885Z",
        "deleted_at": null,
        "owner_username": "FlaviaCarvalho",
        "tabcoins": 3,
        "tabcoins_credit": 2,
        "tabcoins_debit": 0,
        "children_deep_count": 0
    },
    {
        "id": "e05cc976-afd1-4591-84ec-f554939cea77",
        "owner_id": "f21f2950-7d7d-45cd-93f2-edbb6165e6cd",
        "parent_id": null,
        "slug": "pesquisa-do-google-demonstra-que-tamanho-dos-modelos-de-linguagem-importam",
        "title": "Pesquisa do Google demonstra que tamanho dos modelos de linguagem importam",
        "status": "published",
        "type": "content",
        "source_url": "https://ai.googleblog.com/2022/11/characterizing-emergent-phenomena-in.html",
        "created_at": "2022-11-14T14:25:30.973Z",
        "updated_at": "2022-11-14T14:25:30.973Z",
        "published_at": "2022-11-14T14:25:30.998Z",
        "deleted_at": null,
        "owner_username": "FlaviaCarvalho",
        "tabcoins": 1,
        "tabcoins_credit": 0,
        "tabcoins_debit": 0,
        "children_deep_count": 0
    },
    {
        "id": "2506eecc-d95c-4035-94f0-23640e9b5991",
        "owner_id": "f21f2950-7d7d-45cd-93f2-edbb6165e6cd",
        "parent_id": null,
        "slug": "deviantart-lanca-dreamup-gerador-de-imagens-baseado-em-ia-seguro-e-justo",
        "title": "DeviantArt lan\u00e7a DreamUp, gerador de imagens baseado em IA \u201cseguro e justo\u201d",
        "status": "published",
        "type": "content",
        "source_url": "https://www.engadget.com/deviant-art-is-launching-its-own-ai-art-generator-140006449.html",
        "created_at": "2022-11-14T14:23:27.306Z",
        "updated_at": "2022-11-14T14:23:27.306Z",
        "published_at": "2022-11-14T14:23:27.351Z",
        "deleted_at": null,
        "owner_username": "FlaviaCarvalho",
        "tabcoins": 1,
        "tabcoins_credit": 0,
        "tabcoins_debit": 0,
        "children_deep_count": 0
    },
    {
        "id": "2f0a609e-f086-4af0-b8fc-5bb41ecbae4f",
        "owner_id": "f21f2950-7d7d-45cd-93f2-edbb6165e6cd",
        "parent_id": null,
        "slug": "justica-do-trabalho-descobre-fraude-na-emissao-de-certificados-digitais-e-suspende-acesso-a-sistemas-de-pagamento-eletronico-de-alvaras-em-todo-o-pais",
        "title": "Justi\u00e7a do Trabalho descobre fraude na emiss\u00e3o de certificados digitais e suspende acesso a sistemas de pagamento eletr\u00f4nico de alvar\u00e1s em todo o pa\u00eds",
        "status": "published",
        "type": "content",
        "source_url": "https://www.cisoadvisor.com.br/fraude-em-certificados-suspende-pagamentos-na-justica-do-trabalho/",
        "created_at": "2022-11-14T14:20:49.849Z",
        "updated_at": "2022-11-14T14:20:49.849Z",
        "published_at": "2022-11-14T14:20:49.867Z",
        "deleted_at": null,
        "owner_username": "FlaviaCarvalho",
        "tabcoins": 1,
        "tabcoins_credit": 0,
        "tabcoins_debit": 0,
        "children_deep_count": 1
    },
    {
        "id": "6fdbb726-2a04-40ce-b84b-00c4963e6da2",
        "owner_id": "f21f2950-7d7d-45cd-93f2-edbb6165e6cd",
        "parent_id": null,
        "slug": "javascript-continua-como-a-maior-comunidade-em-programacao-mostra-pesquisa-da-slashdata",
        "title": "JavaScript continua como a maior comunidade em programa\u00e7\u00e3o, mostra pesquisa da SlashData",
        "status": "published",
        "type": "content",
        "source_url": "https://www.zdnet.com/article/software-development-is-evolving-and-so-is-what-developers-are-interested-in/",
        "created_at": "2022-11-14T14:19:04.231Z",
        "updated_at": "2022-11-14T14:19:04.231Z",
        "published_at": "2022-11-14T14:19:04.253Z",
        "deleted_at": null,
        "owner_username": "FlaviaCarvalho",
        "tabcoins": 2,
        "tabcoins_credit": 1,
        "tabcoins_debit": 0,
        "children_deep_count": 0
    },
    {
        "id": "c531c362-828f-465c-b566-c82af292418f",
        "owner_id": "f21f2950-7d7d-45cd-93f2-edbb6165e6cd",
        "parent_id": null,
        "slug": "corretora-ftx-teria-sofrido-ataque-hacker-e-analistas-desconfiam-de-ceo",
        "title": "Corretora FTX teria sofrido ataque hacker e analistas desconfiam de CEO",
        "status": "published",
        "type": "content",
        "source_url": null,
        "created_at": "2022-11-14T14:15:39.052Z",
        "updated_at": "2022-11-14T14:15:39.052Z",
        "published_at": "2022-11-14T14:15:39.072Z",
        "deleted_at": null,
        "owner_username": "FlaviaCarvalho",
        "tabcoins": 1,
        "tabcoins_credit": 0,
        "tabcoins_debit": 0,
        "children_deep_count": 0
    },
    {
        "id": "3a6a5d41-952c-434c-b6ad-3aa13cab2026",
        "owner_id": "f21f2950-7d7d-45cd-93f2-edbb6165e6cd",
        "parent_id": null,
        "slug": "palacio-do-planalto-formata-todos-os-computadores-apos-deteccao-de-ataque-ransomware",
        "title": "Pal\u00e1cio do Planalto formata todos os computadores ap\u00f3s detec\u00e7\u00e3o de ataque ransomware",
        "status": "published",
        "type": "content",
        "source_url": "https://www.tecmundo.com.br/seguranca/254260-palacio-planalto-formata-computadores-suposta-ameaca.htm",
        "created_at": "2022-11-14T14:13:32.285Z",
        "updated_at": "2022-11-14T14:13:32.285Z",
        "published_at": "2022-11-14T14:13:32.313Z",
        "deleted_at": null,
        "owner_username": "FlaviaCarvalho",
        "tabcoins": 1,
        "tabcoins_credit": 0,
        "tabcoins_debit": 0,
        "children_deep_count": 0
    },
    {
        "id": "6289b2cd-b0bd-4b39-abee-5a4c4ba7aa9c",
        "owner_id": "95239240-6e12-4a65-a213-aa778c467483",
        "parent_id": null,
        "slug": "arquivo-contendo-todos-os-conteudos-do-tabnews-e-algumas-curiosidades",
        "title": "Arquivo contendo todos os conte\u00fados do tabnews (E algumas curiosidades)",
        "status": "published",
        "type": "content",
        "source_url": "https://github.com/33gustavo33/tabnews-fetch-all-contents",
        "created_at": "2022-11-14T07:17:26.660Z",
        "updated_at": "2022-11-15T07:05:24.858Z",
        "published_at": "2022-11-14T07:17:26.682Z",
        "deleted_at": null,
        "owner_username": "Gustavo33",
        "tabcoins": 16,
        "tabcoins_credit": 15,
        "tabcoins_debit": 0,
        "children_deep_count": 10
    },
    {
        "id": "893b2539-f9c5-4675-ad7e-2ab1f58b66d9",
        "owner_id": "1690aa5c-bab5-4081-bc59-7cebb00f90a9",
        "parent_id": null,
        "slug": "uma-forma-automatica-de-organizar-seu-codigo-em-flask",
        "title": "Uma forma automatica de organizar seu c\u00f3digo em flask!",
        "status": "published",
        "type": "content",
        "source_url": null,
        "created_at": "2022-11-13T16:17:47.883Z",
        "updated_at": "2022-11-15T23:22:17.966Z",
        "published_at": "2022-11-13T16:17:47.917Z",
        "deleted_at": null,
        "owner_username": "viinilv",
        "tabcoins": 9,
        "tabcoins_credit": 8,
        "tabcoins_debit": 0,
        "children_deep_count": 2
    },
    {
        "id": "79645154-519d-486c-bcd6-1a983c2ede07",
        "owner_id": "3315922c-05e3-4432-a501-65df48984d90",
        "parent_id": null,
        "slug": "alguns-nomes-de-usuario-do-telegram-ja-foram-vendidos-por-mais-de-1-milhao-de-dolares",
        "title": "Alguns nomes de usu\u00e1rio do Telegram j\u00e1 foram vendidos por mais de 1 milh\u00e3o de d\u00f3lares",
        "status": "published",
        "type": "content",
        "source_url": "https://fragment.com/",
        "created_at": "2022-11-13T10:55:17.692Z",
        "updated_at": "2022-11-13T12:40:08.577Z",
        "published_at": "2022-11-13T10:55:17.722Z",
        "deleted_at": null,
        "owner_username": "rafael",
        "tabcoins": 8,
        "tabcoins_credit": 7,
        "tabcoins_debit": 0,
        "children_deep_count": 1
    },
    {
        "id": "bb3dd13d-034e-416b-9893-5529dd1f1b3e",
        "owner_id": "3b2e0c42-d529-491f-a944-b11711e7808f",
        "parent_id": null,
        "slug": "bohr-io-plataforma-de-deploy-fullstack-brasileira",
        "title": "Pitch: bohr.io - plataforma de deploy fullstack brasileira!",
        "status": "published",
        "type": "content",
        "source_url": null,
        "created_at": "2022-11-13T07:44:47.352Z",
        "updated_at": "2022-11-13T14:28:42.977Z",
        "published_at": "2022-11-13T07:44:47.375Z",
        "deleted_at": null,
        "owner_username": "boemekeld",
        "tabcoins": 26,
        "tabcoins_credit": 25,
        "tabcoins_debit": 0,
        "children_deep_count": 23
    },
    {
        "id": "8fe035d3-8cac-48b0-a524-a5583a7e1410",
        "owner_id": "c8f6e9b5-3ee1-492c-bf0f-7ac40ccdf99a",
        "parent_id": null,
        "slug": "openssl-lanca-atualizacao-para-corrigir-vulnerabilidade-critica",
        "title": "[NEWS] OpenSSL lan\u00e7a atualiza\u00e7\u00e3o para corrigir vulnerabilidade cr\u00edtica",
        "status": "published",
        "type": "content",
        "source_url": "https://www.tecmundo.com.br/seguranca/253834-openssl-lanca-atualizacao-corrigir-vulnerabilidade-critica.htm",
        "created_at": "2022-11-13T02:22:00.796Z",
        "updated_at": "2022-11-22T12:12:17.763Z",
        "published_at": "2022-11-13T02:22:00.805Z",
        "deleted_at": null,
        "owner_username": "hebertcisco",
        "tabcoins": 6,
        "tabcoins_credit": 5,
        "tabcoins_debit": 0,
        "children_deep_count": 0
    },
    {
        "id": "dea413d5-70bd-4f6d-b08e-5403fd52d85c",
        "owner_id": "c8f6e9b5-3ee1-492c-bf0f-7ac40ccdf99a",
        "parent_id": null,
        "slug": "o-que-e-mdr-e-por-que-voce-precisara-dele",
        "title": "[SECURITY] O que \u00e9 MDR e por que voc\u00ea precisar\u00e1 dele?",
        "status": "published",
        "type": "content",
        "source_url": "https://www.tecmundo.com.br/seguranca/253813-mdr-que-voce-precisara-dele.htm",
        "created_at": "2022-11-13T02:17:13.314Z",
        "updated_at": "2022-11-22T12:12:04.755Z",
        "published_at": "2022-11-13T02:17:13.353Z",
        "deleted_at": null,
        "owner_username": "hebertcisco",
        "tabcoins": 6,
        "tabcoins_credit": 5,
        "tabcoins_debit": 0,
        "children_deep_count": 0
    },
    {
        "id": "398f8c5b-1a45-48df-bfa8-a25b76ff2157",
        "owner_id": "c8f6e9b5-3ee1-492c-bf0f-7ac40ccdf99a",
        "parent_id": null,
        "slug": "camera-montada-no-pulso-captura-o-corpo-inteiro-em-3d",
        "title": "C\u00e2mera montada no pulso captura o corpo inteiro em 3D",
        "status": "published",
        "type": "content",
        "source_url": "https://www.inovacaotecnologica.com.br/noticias/noticia.php?artigo=camera-montada-pulso-captura-corpo-inteiro-3d&id=010150221109",
        "created_at": "2022-11-13T01:50:07.722Z",
        "updated_at": "2022-11-13T01:50:07.722Z",
        "published_at": "2022-11-13T01:50:07.740Z",
        "deleted_at": null,
        "owner_username": "hebertcisco",
        "tabcoins": 8,
        "tabcoins_credit": 7,
        "tabcoins_debit": 0,
        "children_deep_count": 0
    },
    {
        "id": "f5e64796-98bc-43a8-b2aa-13234c853a51",
        "owner_id": "3394355a-e7a6-485e-b367-841693e615d5",
        "parent_id": null,
        "slug": "trabalho-portatil",
        "title": "Trabalho \"Port\u00e1til\"",
        "status": "published",
        "type": "content",
        "source_url": null,
        "created_at": "2022-11-13T01:31:38.484Z",
        "updated_at": "2022-11-13T01:31:38.484Z",
        "published_at": "2022-11-13T01:31:38.510Z",
        "deleted_at": null,
        "owner_username": "bardsnight",
        "tabcoins": 7,
        "tabcoins_credit": 6,
        "tabcoins_debit": 0,
        "children_deep_count": 7
    },
    {
        "id": "34bf2385-4cec-4e0d-8177-d12da9c4788d",
        "owner_id": "c4586fa9-21d0-4976-9630-01e80cd460e1",
        "parent_id": null,
        "slug": "canada-quer-atrair-1-4-milhao-de-imigrantes-ate-2025",
        "title": "Canad\u00e1 quer atrair 1,4 milh\u00e3o de imigrantes at\u00e9 2025",
        "status": "published",
        "type": "content",
        "source_url": "https://www.bbc.com/portuguese/internacional-63515652",
        "created_at": "2022-11-13T00:35:30.741Z",
        "updated_at": "2022-11-13T00:35:30.741Z",
        "published_at": "2022-11-13T00:35:30.810Z",
        "deleted_at": null,
        "owner_username": "felipsbreno",
        "tabcoins": 8,
        "tabcoins_credit": 7,
        "tabcoins_debit": 0,
        "children_deep_count": 0
    },
    {
        "id": "f24bde80-bbf4-4b20-8448-413bbd219224",
        "owner_id": "07ea33ea-78bd-4578-bad2-1cf5323cab07",
        "parent_id": null,
        "slug": "bolhas-de-sabao-interativo-experimento",
        "title": "Bolhas de sab\u00e3o interativo (experimento)",
        "status": "published",
        "type": "content",
        "source_url": null,
        "created_at": "2022-11-12T22:44:40.915Z",
        "updated_at": "2022-11-12T22:44:40.915Z",
        "published_at": "2022-11-12T22:44:40.942Z",
        "deleted_at": null,
        "owner_username": "filipedeschamps",
        "tabcoins": 8,
        "tabcoins_credit": 7,
        "tabcoins_debit": 0,
        "children_deep_count": 0
    },
    {
        "id": "d2c17969-f36f-41a8-9684-1edea8854410",
        "owner_id": "07ea33ea-78bd-4578-bad2-1cf5323cab07",
        "parent_id": null,
        "slug": "mario-souto-e-erick-wendel-sao-homenageados-pelo-github",
        "title": "Mario Souto e Erick Wendel s\u00e3o homenageados pelo GitHub!",
        "status": "published",
        "type": "content",
        "source_url": "https://exame.com/invest/mercados/jovens-periferia-sao-paulo-estrelas-programacao-eua/",
        "created_at": "2022-11-12T16:20:44.391Z",
        "updated_at": "2022-11-12T16:20:44.391Z",
        "published_at": "2022-11-12T16:20:44.428Z",
        "deleted_at": null,
        "owner_username": "filipedeschamps",
        "tabcoins": 11,
        "tabcoins_credit": 10,
        "tabcoins_debit": 0,
        "children_deep_count": 6
    },
    {
        "id": "f1f9e4da-b232-4beb-abd5-2ffa34dbd82f",
        "owner_id": "16518389-0a24-4c9b-8cb6-452314f44a29",
        "parent_id": null,
        "slug": "nim-uma-linguagem-que-deveria-ter-mais-reconhecimento",
        "title": "Nim: uma linguagem que deveria ter mais reconhecimento",
        "status": "published",
        "type": "content",
        "source_url": "https://nim-lang.org/",
        "created_at": "2022-11-12T15:36:20.771Z",
        "updated_at": "2022-11-12T15:36:20.771Z",
        "published_at": "2022-11-12T15:36:20.812Z",
        "deleted_at": null,
        "owner_username": "1MarcosDev",
        "tabcoins": 13,
        "tabcoins_credit": 12,
        "tabcoins_debit": 0,
        "children_deep_count": 1
    },
    {
        "id": "e5f4566a-d45e-4b1d-a56b-908697cea140",
        "owner_id": "c4586fa9-21d0-4976-9630-01e80cd460e1",
        "parent_id": null,
        "slug": "github-anuncia-funcao-para-desenvolver-por-voz-e-copilot-para-empresas",
        "title": "GitHub anuncia fun\u00e7\u00e3o para desenvolver por voz",
        "status": "published",
        "type": "content",
        "source_url": "https://www.tecmundo.com.br/mercado/254147-hey-github-desenvolver-voz-copilot-para-empresas.htm",
        "created_at": "2022-11-12T06:50:00.521Z",
        "updated_at": "2022-11-12T06:50:20.417Z",
        "published_at": "2022-11-12T06:50:00.553Z",
        "deleted_at": null,
        "owner_username": "felipsbreno",
        "tabcoins": 3,
        "tabcoins_credit": 3,
        "tabcoins_debit": -1,
        "children_deep_count": 0
    },
    {
        "id": "64aae18f-7363-4cd4-b0fd-f5e73f8d664e",
        "owner_id": "f814c321-f0d7-49f2-852b-a39e4805fcda",
        "parent_id": null,
        "slug": "web-scraper-dinamico-com-nodejs",
        "title": "Web Scraper Din\u00e2mico com NodeJs?",
        "status": "published",
        "type": "content",
        "source_url": null,
        "created_at": "2022-11-12T04:13:41.581Z",
        "updated_at": "2022-11-12T04:13:41.581Z",
        "published_at": "2022-11-12T04:13:41.606Z",
        "deleted_at": null,
        "owner_username": "RodrigoC",
        "tabcoins": 2,
        "tabcoins_credit": 1,
        "tabcoins_debit": 0,
        "children_deep_count": 4
    },
    {
        "id": "faae24ce-28d7-4f64-8435-c21867152745",
        "owner_id": "cd745c6f-2384-4557-9fdc-a6839d6dd141",
        "parent_id": null,
        "slug": "github-codespaces-agora-funciona-em-contas-gratuitas",
        "title": "Github Codespaces agora funciona em contas gratuitas",
        "status": "published",
        "type": "content",
        "source_url": "https://github.blog/changelog/2022-11-09-codespaces-for-free-and-pro-accounts/",
        "created_at": "2022-11-11T23:21:29.222Z",
        "updated_at": "2022-11-11T23:26:17.776Z",
        "published_at": "2022-11-11T23:21:29.246Z",
        "deleted_at": null,
        "owner_username": "jonathanArgentao",
        "tabcoins": 10,
        "tabcoins_credit": 9,
        "tabcoins_debit": 0,
        "children_deep_count": 1
    },
    {
        "id": "913d2de5-a4d3-4c89-adbc-07cb8c01b8da",
        "owner_id": "07ea33ea-78bd-4578-bad2-1cf5323cab07",
        "parent_id": null,
        "slug": "cada-visita-nesta-pagina-deteriora-a-imagem-principal-experimento",
        "title": "Cada visita nesta p\u00e1gina deteriora a imagem principal (experimento)",
        "status": "published",
        "type": "content",
        "source_url": null,
        "created_at": "2022-11-11T22:35:55.522Z",
        "updated_at": "2022-11-11T22:35:55.522Z",
        "published_at": "2022-11-11T22:35:55.543Z",
        "deleted_at": null,
        "owner_username": "filipedeschamps",
        "tabcoins": 14,
        "tabcoins_credit": 14,
        "tabcoins_debit": -1,
        "children_deep_count": 0
    },
    {
        "id": "ee10893e-5fbf-44ef-99bf-259ea8fa2f76",
        "owner_id": "c4586fa9-21d0-4976-9630-01e80cd460e1",
        "parent_id": null,
        "slug": "x-team-radio",
        "title": "X-Team Radio",
        "status": "published",
        "type": "content",
        "source_url": "https://radio.x-team.com/",
        "created_at": "2022-11-11T20:14:02.616Z",
        "updated_at": "2022-11-11T20:32:39.421Z",
        "published_at": "2022-11-11T20:14:02.641Z",
        "deleted_at": null,
        "owner_username": "felipsbreno",
        "tabcoins": 7,
        "tabcoins_credit": 6,
        "tabcoins_debit": 0,
        "children_deep_count": 5
    },
    {
        "id": "06226503-7d32-4a37-9f7e-605f05dc9f75",
        "owner_id": "f21f2950-7d7d-45cd-93f2-edbb6165e6cd",
        "parent_id": null,
        "slug": "fabricante-chinesa-jac-motors-planeja-vender-apenas-carros-eletricos-no-brasil",
        "title": "Fabricante chinesa JAC Motors planeja vender apenas carros el\u00e9tricos no Brasil",
        "status": "published",
        "type": "content",
        "source_url": "https://canaltech.com.br/carros/jac-abandona-carros-a-combustao-e-vai-vender-apenas-eletricos-no-brasil-229109/",
        "created_at": "2022-11-11T19:55:01.204Z",
        "updated_at": "2022-11-11T19:55:01.204Z",
        "published_at": "2022-11-11T19:55:01.236Z",
        "deleted_at": null,
        "owner_username": "FlaviaCarvalho",
        "tabcoins": 2,
        "tabcoins_credit": 1,
        "tabcoins_debit": 0,
        "children_deep_count": 0
    },
    {
        "id": "55349ce9-f24d-49e5-87d6-e494a81d8b88",
        "owner_id": "f21f2950-7d7d-45cd-93f2-edbb6165e6cd",
        "parent_id": null,
        "slug": "ceo-e-fundador-da-ftx-renuncia-ao-cargo-e-empresa-entra-com-pedido-de-falencia",
        "title": "CEO e fundador da FTX renuncia ao cargo e empresa entra com pedido de fal\u00eancia",
        "status": "published",
        "type": "content",
        "source_url": "https://arstechnica.com/tech-policy/2022/11/sam-bankman-frieds-32-billion-ftx-crypto-empire-files-for-bankruptcy/",
        "created_at": "2022-11-11T19:18:55.963Z",
        "updated_at": "2022-11-11T19:18:55.963Z",
        "published_at": "2022-11-11T19:18:55.973Z",
        "deleted_at": null,
        "owner_username": "FlaviaCarvalho",
        "tabcoins": 2,
        "tabcoins_credit": 1,
        "tabcoins_debit": 0,
        "children_deep_count": 0
    },
    {
        "id": "3250228f-e3a0-4d83-b45f-c9a7badd9445",
        "owner_id": "af3c25a4-6157-491d-a0a5-3d677affbb7f",
        "parent_id": null,
        "slug": "a-melhor-maneira-de-se-manter-atualizado",
        "title": "A MELHOR maneira de se manter atualizado no mundo da tecnologia",
        "status": "published",
        "type": "content",
        "source_url": null,
        "created_at": "2022-11-11T18:52:14.245Z",
        "updated_at": "2022-11-11T18:52:27.253Z",
        "published_at": "2022-11-11T18:52:14.266Z",
        "deleted_at": null,
        "owner_username": "ArthurMadureira",
        "tabcoins": 11,
        "tabcoins_credit": 10,
        "tabcoins_debit": 0,
        "children_deep_count": 2
    },
    {
        "id": "adc7e209-1cc9-443b-8aa4-bb370d0b2585",
        "owner_id": "f21f2950-7d7d-45cd-93f2-edbb6165e6cd",
        "parent_id": null,
        "slug": "novo-projeto-de-lei-propoe-que-anatel-regulamente-plataformas-digitais",
        "title": "Novo projeto de lei prop\u00f5e que Anatel regulamente plataformas digitais",
        "status": "published",
        "type": "content",
        "source_url": "https://www.mobiletime.com.br/noticias/11/11/2022/regulamentacao-de-plataformas-digitais-pela-anatel-e-proposta-em-novo-projeto-de-lei/",
        "created_at": "2022-11-11T18:18:11.486Z",
        "updated_at": "2022-11-11T18:18:11.486Z",
        "published_at": "2022-11-11T18:18:11.511Z",
        "deleted_at": null,
        "owner_username": "FlaviaCarvalho",
        "tabcoins": 2,
        "tabcoins_credit": 1,
        "tabcoins_debit": 0,
        "children_deep_count": 0
    },
    {
        "id": "5b5ac5ef-dade-4710-80d2-3317d6b089e5",
        "owner_id": "804492ab-0fd9-4507-a1a3-a969e10c24bd",
        "parent_id": null,
        "slug": "rust-a-linguagem-em-que-todos-deveriam-estar-de-olho",
        "title": "Rust: a linguagem em que todos deveriam estar de olho",
        "status": "published",
        "type": "content",
        "source_url": "https://codecon.substack.com/p/rust-a-linguagem-em-que-todos-deveriam",
        "created_at": "2022-11-11T17:12:25.491Z",
        "updated_at": "2022-11-11T17:12:25.491Z",
        "published_at": "2022-11-11T17:12:25.519Z",
        "deleted_at": null,
        "owner_username": "gabrielnunes",
        "tabcoins": 20,
        "tabcoins_credit": 19,
        "tabcoins_debit": 0,
        "children_deep_count": 11
    },
    {
        "id": "23a5db89-17d4-49b8-a788-404b23df96fe",
        "owner_id": "c4586fa9-21d0-4976-9630-01e80cd460e1",
        "parent_id": null,
        "slug": "mergear-um-codigo-sem-revisao-e-uma-boa",
        "title": "Mergear um c\u00f3digo sem revis\u00e3o \u00e9 uma boa ?",
        "status": "published",
        "type": "content",
        "source_url": null,
        "created_at": "2022-11-11T16:32:08.958Z",
        "updated_at": "2022-11-11T17:21:42.699Z",
        "published_at": "2022-11-11T16:32:08.986Z",
        "deleted_at": null,
        "owner_username": "felipsbreno",
        "tabcoins": 6,
        "tabcoins_credit": 5,
        "tabcoins_debit": 0,
        "children_deep_count": 7
    },
    {
        "id": "e0114760-ef6e-4ba2-afb7-b292c78809db",
        "owner_id": "f21f2950-7d7d-45cd-93f2-edbb6165e6cd",
        "parent_id": null,
        "slug": "aplicativo-permite-executar-o-stable-diffusion-localmente-em-iphones",
        "title": "Aplicativo permite executar o Stable Diffusion localmente em iPhones",
        "status": "published",
        "type": "content",
        "source_url": "https://arstechnica.com/information-technology/2022/11/stable-diffusion-in-your-pocket-draw-things-brings-ai-images-to-iphone/",
        "created_at": "2022-11-11T14:02:58.875Z",
        "updated_at": "2022-11-11T14:02:58.875Z",
        "published_at": "2022-11-11T14:02:58.904Z",
        "deleted_at": null,
        "owner_username": "FlaviaCarvalho",
        "tabcoins": 2,
        "tabcoins_credit": 1,
        "tabcoins_debit": 0,
        "children_deep_count": 0
    },
    {
        "id": "5f49719e-3b90-4661-990a-128cf60a51a1",
        "owner_id": "f21f2950-7d7d-45cd-93f2-edbb6165e6cd",
        "parent_id": null,
        "slug": "vulnerabilidade-permite-que-invasores-obtenham-acesso-completo-a-qualquer-smartphone-google-pixel-mesmo-com-o-dispositivo-bloqueado",
        "title": "Vulnerabilidade permite que invasores obtenham acesso completo a qualquer smartphone Google Pixel, mesmo com o dispositivo bloqueado",
        "status": "published",
        "type": "content",
        "source_url": "https://bugs.xdavidhu.me/google/2022/11/10/accidental-70k-google-pixel-lock-screen-bypass/",
        "created_at": "2022-11-11T14:00:36.785Z",
        "updated_at": "2022-11-11T14:00:36.785Z",
        "published_at": "2022-11-11T14:00:36.821Z",
        "deleted_at": null,
        "owner_username": "FlaviaCarvalho",
        "tabcoins": 3,
        "tabcoins_credit": 2,
        "tabcoins_debit": 0,
        "children_deep_count": 2
    },
    {
        "id": "9f358c9c-76cb-41f1-b125-5bf48a6a59ff",
        "owner_id": "f21f2950-7d7d-45cd-93f2-edbb6165e6cd",
        "parent_id": null,
        "slug": "entidades-e-empresas-pedem-mais-agilidade-na-aprovacao-da-lei-das-moedas-digitais",
        "title": "Entidades e empresas pedem mais agilidade na aprova\u00e7\u00e3o da lei das moedas digitais",
        "status": "published",
        "type": "content",
        "source_url": "https://canaltech.com.br/criptomoedas/carta-enviada-a-camara-pede-mais-agilidade-na-aprovacao-da-lei-das-criptomoedas-229067/",
        "created_at": "2022-11-11T13:57:36.148Z",
        "updated_at": "2022-11-11T13:57:36.148Z",
        "published_at": "2022-11-11T13:57:36.180Z",
        "deleted_at": null,
        "owner_username": "FlaviaCarvalho",
        "tabcoins": 1,
        "tabcoins_credit": 0,
        "tabcoins_debit": 0,
        "children_deep_count": 0
    },
    {
        "id": "aa0b3d56-0448-42d9-baa2-21d08e38a818",
        "owner_id": "f21f2950-7d7d-45cd-93f2-edbb6165e6cd",
        "parent_id": null,
        "slug": "agencia-de-seguranca-nacional-dos-eua-orienta-que-organizacoes-mudem-para-linguagens-de-programacao-com-memory-safety",
        "title": "Ag\u00eancia de Seguran\u00e7a Nacional dos EUA orienta que organiza\u00e7\u00f5es mudem para linguagens de programa\u00e7\u00e3o com memory safety",
        "status": "published",
        "type": "content",
        "source_url": "https://www.nsa.gov/Press-Room/News-Highlights/Article/Article/3215760/nsa-releases-guidance-on-how-to-protect-against-software-memory-safety-issues/",
        "created_at": "2022-11-11T13:54:48.408Z",
        "updated_at": "2022-11-11T13:54:48.408Z",
        "published_at": "2022-11-11T13:54:48.434Z",
        "deleted_at": null,
        "owner_username": "FlaviaCarvalho",
        "tabcoins": 5,
        "tabcoins_credit": 4,
        "tabcoins_debit": 0,
        "children_deep_count": 2
    },
    {
        "id": "8fac4ca9-c3d0-49a5-b325-8fa7c0b7fa29",
        "owner_id": "f21f2950-7d7d-45cd-93f2-edbb6165e6cd",
        "parent_id": null,
        "slug": "elon-musk-convoca-funcionarios-do-twitter-para-reuniao-de-emergencia-e-alerta-que-falencia-nao-esta-fora-de-cogitacao",
        "title": "Elon Musk convoca funcion\u00e1rios do Twitter para reuni\u00e3o de emerg\u00eancia e alerta que \u201cfal\u00eancia n\u00e3o est\u00e1 fora de cogita\u00e7\u00e3o\u201d",
        "status": "published",
        "type": "content",
        "source_url": "https://9to5mac.com/2022/11/10/twitter-bankruptcy-ads-collapse/",
        "created_at": "2022-11-11T13:52:48.168Z",
        "updated_at": "2022-11-11T13:52:48.168Z",
        "published_at": "2022-11-11T13:52:48.192Z",
        "deleted_at": null,
        "owner_username": "FlaviaCarvalho",
        "tabcoins": 3,
        "tabcoins_credit": 2,
        "tabcoins_debit": 0,
        "children_deep_count": 2
    },
    {
        "id": "3ba16c92-9c80-4cc1-8c40-ed4b7a96488e",
        "owner_id": "110cc974-4c56-4074-afbc-81ce22aa6013",
        "parent_id": null,
        "slug": "novo-mecanismo-de-busca-preve-links-em-vez-de-pesquisar-por-textos",
        "title": "Novo mecanismo de busca prev\u00ea links em vez de pesquisar por textos",
        "status": "published",
        "type": "content",
        "source_url": "https://metaphor.systems",
        "created_at": "2022-11-11T01:01:42.390Z",
        "updated_at": "2022-11-11T01:01:42.390Z",
        "published_at": "2022-11-11T01:01:42.470Z",
        "deleted_at": null,
        "owner_username": "gugadeschamps",
        "tabcoins": 7,
        "tabcoins_credit": 6,
        "tabcoins_debit": 0,
        "children_deep_count": 0
    },
    {
        "id": "f3628008-85da-48fa-b170-b1014ef3e25d",
        "owner_id": "1690aa5c-bab5-4081-bc59-7cebb00f90a9",
        "parent_id": null,
        "slug": "vou-participar-da-minha-primeira-entrevista-de-tecnologia",
        "title": "Vou participar da minha primeira entrevista de tecnologia!",
        "status": "published",
        "type": "content",
        "source_url": null,
        "created_at": "2022-11-10T23:33:39.638Z",
        "updated_at": "2022-11-10T23:33:39.638Z",
        "published_at": "2022-11-10T23:33:39.664Z",
        "deleted_at": null,
        "owner_username": "viinilv",
        "tabcoins": 4,
        "tabcoins_credit": 3,
        "tabcoins_debit": 0,
        "children_deep_count": 2
    },
    {
        "id": "50f5b9d9-6cc1-432a-94dd-4070313a2d14",
        "owner_id": "f21f2950-7d7d-45cd-93f2-edbb6165e6cd",
        "parent_id": null,
        "slug": "aplicativo-da-cupula-cop27-no-egito-e-uma-risco-de-ciberseguranca-alertam-especialistas",
        "title": "Aplicativo da c\u00fapula clim\u00e1tica COP27 no Egito \u00e9 um risco de ciberseguran\u00e7a, alertam especialistas",
        "status": "published",
        "type": "content",
        "source_url": "https://www.politico.eu/article/cop-27-climate-change-app-cybersecurity-weapon-risks/",
        "created_at": "2022-11-10T22:31:15.973Z",
        "updated_at": "2022-11-10T22:32:08.787Z",
        "published_at": "2022-11-10T22:31:15.993Z",
        "deleted_at": null,
        "owner_username": "FlaviaCarvalho",
        "tabcoins": 2,
        "tabcoins_credit": 1,
        "tabcoins_debit": 0,
        "children_deep_count": 0
    },
    {
        "id": "19ff75c3-2ada-43ec-be16-a909e2292c63",
        "owner_id": "b796d561-e9ab-46d9-8bf6-251be36e96e5",
        "parent_id": null,
        "slug": "novo-buscador-de-codigo-do-github",
        "title": "Novo \"buscador\" de Codigo do github",
        "status": "published",
        "type": "content",
        "source_url": "https://github.com/features/code-search",
        "created_at": "2022-11-10T21:20:03.926Z",
        "updated_at": "2022-11-10T21:20:03.926Z",
        "published_at": "2022-11-10T21:20:03.936Z",
        "deleted_at": null,
        "owner_username": "CarlosZiegler",
        "tabcoins": 7,
        "tabcoins_credit": 6,
        "tabcoins_debit": 0,
        "children_deep_count": 0
    },
    {
        "id": "29c7d73b-4d58-4842-b00a-f2567adae065",
        "owner_id": "f21f2950-7d7d-45cd-93f2-edbb6165e6cd",
        "parent_id": null,
        "slug": "plataforma-de-design-canva-implementa-modelo-de-ia-do-stable-diffusion-para-lancar-seu-proprio-recurso-de-geracao-de-imagens",
        "title": "Plataforma de design Canva implementa modelo de IA do Stable Diffusion para lan\u00e7ar seu pr\u00f3prio recurso de gera\u00e7\u00e3o de imagens",
        "status": "published",
        "type": "content",
        "source_url": "https://www.theverge.com/2022/11/10/23450965/canva-text-to-image-ai-tool-free-users",
        "created_at": "2022-11-10T20:32:16.984Z",
        "updated_at": "2022-11-10T20:32:16.984Z",
        "published_at": "2022-11-10T20:32:17.013Z",
        "deleted_at": null,
        "owner_username": "FlaviaCarvalho",
        "tabcoins": 4,
        "tabcoins_credit": 3,
        "tabcoins_debit": 0,
        "children_deep_count": 1
    },
    {
        "id": "5a372d51-2829-4e58-afdc-a12631334da4",
        "owner_id": "f21f2950-7d7d-45cd-93f2-edbb6165e6cd",
        "parent_id": null,
        "slug": "apos-acordo-com-a-binance-falhar-ceo-da-ftx-diz-estar-em-negociacoes-para-levantar-capital-e-salvar-a-corretora",
        "title": "Ap\u00f3s acordo com a Binance falhar, CEO da FTX diz estar em negocia\u00e7\u00f5es para levantar capital e salvar a corretora",
        "status": "published",
        "type": "content",
        "source_url": "https://techcrunch.com/2022/11/10/sam-bankman-fried-says-alameda-research-to-wind-down-trading-ftx-attempting-to-raise-capital/",
        "created_at": "2022-11-10T19:21:12.990Z",
        "updated_at": "2022-11-10T19:21:12.990Z",
        "published_at": "2022-11-10T19:21:13.006Z",
        "deleted_at": null,
        "owner_username": "FlaviaCarvalho",
        "tabcoins": 1,
        "tabcoins_credit": 0,
        "tabcoins_debit": 0,
        "children_deep_count": 1
    }
]